tpa_map_functions/__init__.py
tpa_map_functions/helperfuncs/__init__.py
tpa_map_functions/helperfuncs/calc_cosyidcs.py
tpa_map_functions/helperfuncs/concat_tpamaps_ltpl.py
tpa_map_functions/helperfuncs/concat_tpamaps_vehdynsim.py
tpa_map_functions/helperfuncs/import_vehdyninfo.py
tpa_map_functions/helperfuncs/preprocess_ltplrefline.py
tpa_map_functions/helperfuncs/save_tpamap.py
tpa_map_functions/helperfuncs/transform_coordinates_xy2s.py
tpa_map_functions/interface/MapInterface.py
tpa_map_functions/interface/__init__.py
tpa_map_functions/visualization/__init__.py
tpa_map_functions/visualization/visualize_tpamap.py
tpa_map_functions-0.19.dist-info/LICENSE
tpa_map_functions-0.19.dist-info/METADATA
tpa_map_functions-0.19.dist-info/WHEEL
tpa_map_functions-0.19.dist-info/top_level.txt
tpa_map_functions-0.19.dist-info/RECORD
