Metadata-Version: 2.1
Name: tpa-map-functions
Version: 0.19
Summary: Functions to process local acceleration limits for trajectory planning within the TUM Autonomous Motorsports project
Home-page: https://github.com/TUMFTM
Author: Leonhard Hermansdorfer
Author-email: leo.hermansdorfer@tum.de
License: UNKNOWN
Platform: UNKNOWN
Classifier: Programming Language :: Python :: 3
Classifier: Programming Language :: Python :: 3.6
Classifier: Programming Language :: Python :: 3.7
Classifier: Programming Language :: Python :: 3.8
Classifier: License :: OSI Approved :: GNU Lesser General Public License v3 (LGPLv3)
Classifier: Operating System :: OS Independent
License-File: LICENSE
Requires-Dist: numpy (>=1.18.1)
Requires-Dist: ad-interface-functions (>=0.21)
Requires-Dist: trajectory-planning-helpers (>=0.74)
Requires-Dist: pyzmq (>=19.0.2)
Requires-Dist: matplotlib (>=3.3.1)
